manage/__init__.py
manage/__main__.py
manage/auto_import.py
manage/cli.py
manage/commands_collector.py
manage/template.py
pymanage-0.1.15.dist-info/AUTHORS.rst
pymanage-0.1.15.dist-info/LICENSE
pymanage-0.1.15.dist-info/METADATA
pymanage-0.1.15.dist-info/WHEEL
pymanage-0.1.15.dist-info/entry_points.txt
pymanage-0.1.15.dist-info/top_level.txt
pymanage-0.1.15.dist-info/RECORD
