Metadata-Version: 2.1
Name: pymanage
Version: 0.1.15
Summary: Command Line Manager + Interactive Shell for Python Projects
Home-page: https://gitlab.com/jorgeecardona/pymanage
Author: Bruno Rocha, Jorge Cardona
License: ISC license
Keywords: manage
Platform: UNKNOWN
Classifier: Development Status :: 2 - Pre-Alpha
Classifier: Intended Audience :: Developers
Classifier: License :: OSI Approved :: ISC License (ISCL)
Classifier: Natural Language :: English
Classifier: Programming Language :: Python :: 3.5
Classifier: Programming Language :: Python :: 3.6
Classifier: Programming Language :: Python :: 3.7
Classifier: Programming Language :: Python :: 3.8
Requires-Dist: Click (>=7.1)
Requires-Dist: PyYAML (>=5.3)
